{
  "id": "mi86a30diyhlkae10o",
  "title": "At our Research@ Poland event we shared how AI is helping us solve big challenges.",
  "summary": "From AI education to disaster response, see how collaboration is at the heart of the work at Google Research.",
  "content": "<img src=\"https://storage.googleapis.com/gweb-uniblog-publish-prod/images/researchpoland_social.max-600x600.format-webp.webp\">From AI education to disaster response, see how collaboration is at the heart of the work at Google Research.",
  "publishedAt": "2025-11-19T09:00:00.000Z",
  "source": "Google Technology Blog",
  "sourceUrl": "https://blog.google/technology/research/ai-collaboration-poland-2025/",
  "category": "companies",
  "company": "Google",
  "imageUrl": null,
  "tags": [
    "AI",
    "Google"
  ],
  "featured": true
}