{
  "id": "mj4a4ijp5pa7g2xtyzb",
  "title": "Don't Trust, Verify: Building End-to-End Confidential Applications on Google Cloud",
  "summary": "Google Cloud enables end-to-end confidential applications, protecting sensitive data 'in-use' with hardware isolation. The solution combines Confidential Space (TEE/attestation), Oak Functions (private sandbox), and Oak Session (attested end-to-end encryption for scale). This framework anchors user ...",
  "content": "Google Cloud enables end-to-end confidential applications, protecting sensitive data 'in-use' with hardware isolation. The solution combines Confidential Space (TEE/attestation), Oak Functions (private sandbox), and Oak Session (attested end-to-end encryption for scale). This framework anchors user trust in open-source components, proving confidentiality for sensitive workloads like proprietary GenAI models, even when running behind untrusted load balancers.",
  "publishedAt": "2025-12-08T12:35:46.021Z",
  "source": "Google Developers Blog",
  "sourceUrl": "https://developers.googleblog.com/dont-trust-verify-building-end-to-end-confidential-applications-on-google-cloud/",
  "category": "tools",
  "company": "Google",
  "imageUrl": null,
  "tags": [
    "AI",
    "Google"
  ],
  "featured": true
}