{
  "id": "mh9vln4cg4bm09ipqgi",
  "title": "Google Beam is working with the USO to support military families.",
  "summary": "Learn more about Google’s work with the USO and how it plans to launch a program that will enable service members to stay in touch with loved ones.",
  "content": "<img src=\"https://storage.googleapis.com/gweb-uniblog-publish-prod/images/GoogleBeam_CarouselBall.max-600x600.format-webp.webp\">Learn more about Google’s work with the USO and how it plans to launch a program that will enable service members to stay in touch with loved ones.",
  "publishedAt": "2025-10-27T17:45:00.000Z",
  "source": "Google Technology Blog",
  "sourceUrl": "https://blog.google/feed/google-beam-uso-partnership/",
  "category": "companies",
  "company": "Google",
  "imageUrl": null,
  "tags": [
    "Google"
  ],
  "featured": false
}