{
  "id": "mf3ldwvdgh7wincjv4c",
  "title": "New AI-powered live translation and language learning tools in Google Translate",
  "summary": "Google Translate is using AI to make live translation and language learning even more helpful.",
  "content": "<img src=\"https://storage.googleapis.com/gweb-uniblog-publish-prod/images/Translate_with_AI.max-600x600.format-webp.webp\">Google Translate is using AI to make live translation and language learning even more helpful.",
  "publishedAt": "2025-08-26T16:00:00.000Z",
  "source": "Google Technology Blog",
  "sourceUrl": "https://blog.google/products/translate/language-learning-live-translate/",
  "category": "companies",
  "company": "Google",
  "imageUrl": null,
  "tags": [
    "AI",
    "Google"
  ],
  "featured": false
}