{
  "id": "mdw0iz6i8px14f3n7nh",
  "title": "What’s new in NotebookLM: Video Overviews and an upgraded Studio",
  "summary": "NotebookLM launches Video Overviews and upgrades to the Studio panel.",
  "content": "<img src=\"https://storage.googleapis.com/gweb-uniblog-publish-prod/images/VideoOverviewBanner.max-600x600.format-webp.webp\">NotebookLM launches Video Overviews and upgrades to the Studio panel.",
  "publishedAt": "2025-07-29T16:00:00.000Z",
  "source": "Google Technology Blog",
  "sourceUrl": "https://blog.google/technology/google-labs/notebooklm-video-overviews-studio-upgrades/",
  "category": "companies",
  "company": "Google",
  "imageUrl": null,
  "tags": [],
  "featured": true
}